fckprint/__init__.py
fckprint/decorators.py
fckprint/pycompat.py
fckprint/tracer.py
fckprint/utils.py
fckprint/variables.py
fckprint-1.1.2.dist-info/licenses/AUTHORS
fckprint-1.1.2.dist-info/licenses/LICENSE
fckprint-1.1.2.dist-info/METADATA
fckprint-1.1.2.dist-info/WHEEL
fckprint-1.1.2.dist-info/top_level.txt
fckprint-1.1.2.dist-info/RECORD
