Metadata-Version: 2.4
Name: fckprint
Version: 1.1.2
Summary: imagine a world using print for debugging, and we are happy to be not be in it now.
Home-page: https://github.com/SRSWTI/fckprint
Author: SRSWTI Research Labs
Author-email: team@srswti.com
Keywords: debugging monitoring performance security production tracing
Classifier: Environment :: Console
Classifier: Intended Audience :: Developers
Classifier: Programming Language :: Python :: 3.6
Classifier: Programming Language :: Python :: 3.7
Classifier: Programming Language :: Python :: 3.8
Classifier: Programming Language :: Python :: 3.9
Classifier: Programming Language :: Python :: 3.10
Classifier: Programming Language :: Python :: 3.11
Classifier: Programming Language :: Python :: 3.12
Classifier: Programming Language :: Python :: Implementation :: CPython
Classifier: Programming Language :: Python :: Implementation :: PyPy
Classifier: License :: OSI Approved :: MIT License
Classifier: Operating System :: OS Independent
Classifier: Topic :: Software Development :: Debuggers
Classifier: Topic :: Software Development :: Testing
Classifier: Topic :: System :: Monitoring
Classifier: Topic :: System :: Systems Administration
Requires-Python: >=3.6
License-File: LICENSE
License-File: AUTHORS
Provides-Extra: tests
Requires-Dist: pytest; extra == "tests"
Requires-Dist: pytest-cov; extra == "tests"
Provides-Extra: monitoring
Requires-Dist: psutil; extra == "monitoring"
Provides-Extra: full
Requires-Dist: psutil; extra == "full"
Requires-Dist: numpy; extra == "full"
Dynamic: author
Dynamic: author-email
Dynamic: classifier
Dynamic: description
Dynamic: description-content-type
Dynamic: home-page
Dynamic: keywords
Dynamic: license-file
Dynamic: provides-extra
Dynamic: requires-python
Dynamic: summary
